kagami/__init__.py
kagami/unitest.py
kagami/comm/__init__.py
kagami/comm/functional.py
kagami/comm/logger.py
kagami/comm/misc.py
kagami/comm/path.py
kagami/comm/types.py
kagami/dtypes/__init__.py
kagami/dtypes/coreType.py
kagami/dtypes/namedIndex.py
kagami/dtypes/structArray.py
kagami/dtypes/table.py
kagami/portals/__init__.py
kagami/portals/tablePortal.py
kagami/portals/textPortal.py
kagami/portals/webPortal.py
kagami/tests/__init__.py
kagami/tests/comm_tests/__init__.py
kagami/tests/comm_tests/test_functional.py
kagami/tests/comm_tests/test_misc.py
kagami/tests/comm_tests/test_path.py
kagami/tests/comm_tests/test_types.py
kagami/tests/dtypes_tests/__init__.py
kagami/tests/dtypes_tests/test_coreType.py
kagami/tests/dtypes_tests/test_namedIndex.py
kagami/tests/dtypes_tests/test_structArray.py
kagami/tests/dtypes_tests/test_table.py
kagami/tests/portals_tests/__init__.py
kagami/tests/portals_tests/test_tablePortal.py
kagami/tests/portals_tests/test_textPortal.py
kagami/tests/portals_tests/test_webPortal.py
kagami/tests/wrappers_tests/__init__.py
kagami/tests/wrappers_tests/test_binWrapper.py
kagami/tests/wrappers_tests/test_rWrapper.py
kagami/tests/wrappers_tests/test_sqliteWrapper.py
kagami/wrappers/__init__.py
kagami/wrappers/binWrapper.py
kagami/wrappers/rWrapper.py
kagami/wrappers/sqliteWrapper.py
kagami-3.2.3.dist-info/LICENSE
kagami-3.2.3.dist-info/METADATA
kagami-3.2.3.dist-info/WHEEL
kagami-3.2.3.dist-info/top_level.txt
kagami-3.2.3.dist-info/RECORD
