Metadata-Version: 2.1
Name: kagami
Version: 3.2.3
Summary: A framework to support functional programming for computational biology algorithm development
Home-page: https://github.com/akialbz/Kagami
Author: Albert Zhou
Classifier: Topic :: Scientific/Engineering :: Bio-Informatics
Classifier: Topic :: Software Development :: Libraries
Classifier: Programming Language :: Python :: 3
Classifier: License :: OSI Approved :: GNU Lesser General Public License v3 (LGPLv3)
Classifier: Operating System :: POSIX
License-File: LICENSE
Requires-Dist: requests>=2.32.3
Requires-Dist: tables>=3.10.1
Requires-Dist: numpy>=1.26.4
Requires-Dist: pandas>=2.2.3
